vedro_valera_validator/__init__.py
vedro_valera_validator/_valera_validator.py
vedro_valera_validator/py.typed
vedro_valera_validator-1.2.1.dist-info/LICENSE
vedro_valera_validator-1.2.1.dist-info/METADATA
vedro_valera_validator-1.2.1.dist-info/WHEEL
vedro_valera_validator-1.2.1.dist-info/top_level.txt
vedro_valera_validator-1.2.1.dist-info/RECORD
